bits/__init__.py
bits/mongo/__init__.py
bits_mongo-1.0.4.dist-info/METADATA
bits_mongo-1.0.4.dist-info/WHEEL
bits_mongo-1.0.4.dist-info/top_level.txt
bits_mongo-1.0.4.dist-info/RECORD
