Metadata-Version: 2.1
Name: bits-mongo
Version: 1.0.4
Summary: BITS Mongo
Author: Lukas Karlsson
Author-email: karlsson@broadinstitute.org
License: Apache Software License
Platform: UNKNOWN
Requires-Dist: bits-progressbar
Requires-Dist: pymongo
